pubsub/__init__.py
pubsub/main.py
python_publish_subscriber-0.0.1.dist-info/METADATA
python_publish_subscriber-0.0.1.dist-info/WHEEL
python_publish_subscriber-0.0.1.dist-info/top_level.txt
python_publish_subscriber-0.0.1.dist-info/RECORD
