Metadata-Version: 2.1
Name: python-publish-subscriber
Version: 0.0.1
Summary: Python PubSub library
Home-page: https://github.com/MihaiBlebea/python-pubsub
Author: Mihai Blebea
Author-email: mihaiserban.blebea@gmail.com
License: MIT
Keywords: pubsub publisher subscriber
Platform: UNKNOWN
